MANIFEST.in
changelog.rst
readme.rst
setup.py
AuditBWC.egg-info/PKG-INFO
AuditBWC.egg-info/SOURCES.txt
AuditBWC.egg-info/dependency_links.txt
AuditBWC.egg-info/not-zip-safe
AuditBWC.egg-info/requires.txt
AuditBWC.egg-info/top_level.txt
auditbwc/__init__.py
auditbwc/grids.py
auditbwc/version.txt
auditbwc/helpers/__init__.py
auditbwc/helpers/views.py
auditbwc/model/__init__.py
auditbwc/model/declarative.py
auditbwc/model/entities.py
auditbwc/templates/audit_diff.css
auditbwc/templates/audit_diff.html